{
  "application_log_filename": "log/app.log",
  "output_filename": "dataset/vgsales.csv",
  "separator": ",",
  "encoding": "utf-8",
  "start_page": 1,
  "end_page": 2,
  "include_genre": false,
  "base_page_url": "https://www.vgchartz.com/gamedb/?page=",
  "query_parameters": {
    "results": 100,
    "region": "All",
    "boxart": "Both",
    "banner": "Both",
    "ownership": "Both",
    "showmultiplat": "No",
    "order": "Sales",
    "showtotalsales": 1,
    "showpublisher": 1,
    "showvgchartzscore": 1,
    "shownasales": 1,
    "showdeveloper": 1,
    "showcriticscore": 1,
    "showpalsales": 1,
    "showreleasedate": 1,
    "showuserscore": 1,
    "showjapansales": 1,
    "showlastupdate": 1,
    "showothersales": 1,
    "showshipped": 1,
    "keyword": null,
    "console": null,
    "developer": null,
    "publisher": null,
    "goty_year": null,
    "genre": null
  },
  "minimum_sleep_time": 6,
  "maximum_sleep_time": 15,
  "minimum_major_version": 1,
  "maximum_major_version": 56,
  "minimum_minor_version": 1,
  "maximum_minor_version": 10
}
